{"runnerTry": [{"PutRequest": {"Item": {"user_id": {"S": "6bd5f3c04e6b5279aca633c2a245dd9c"}, "activity_id": {"S": "8906bb6b9feb5d919e1649b9b4222ad3"}, "start": {"S": "2017-05-02T18:48:34.979000Z"}, "end": {"S": "2017-05-02T19:21:31.229000Z"}, "type": {"S": "run"}, "distance": {"N": "6.03504"}, "speed": {"N": "10.993621252371918"}, "calories": {"N": "487.328876770041"}, "pace": {"N": "5.45771030515125"}}}}, {"PutRequest": {"Item": {"user_id": {"S": "72eff89c74cc57178e02f103187ad579"}, "activity_id": {"S": "75ac13a2e8575a55b7ab0d474dcf33db"}, "start": {"S": "2017-11-07T18:59:35Z"}, "end": {"S": "2017-11-07T20:04:20Z"}, "type": {"S": "run"}, "distance": {"N": "10.106349609375004"}, "speed": {"N": "9.98980192030478"}, "calories": {"N": "790.9999999999992"}, "heart_rate": {"N": "151.46898263027296"}, "ascent": {"N": "152.64000205993648"}, "descent": {"N": "145.60000228881836"}, "pace": {"N": "6.006125094237048"}}}}, {"PutRequest": {"Item": {"user_id": {"S": "c7e962db02da55209f02fe3d8a86c99d"}, "activity_id": {"S": "86f4537095f25e6ba6600f6a1ca47e07"}, "start": {"S": "2017-12-09T15:52:43.498000Z"}, "end": {"S": "2017-12-09T16:37:53.496000Z"}, "type": {"S": "training"}, "calories": {"N": "159"}}}}, {"PutRequest": {"Item": {"user_id": {"S": "d77908482ed2505ebbf17ef72be2f080"}, "activity_id": {"S": "acbf6366aaf5554da9462f8c1e724a2a"}, "start": {"S": "2018-04-10T19:31:32Z"}, "end": {"S": "2018-04-10T19:42:02.411000Z"}, "type": {"S": "run"}, "distance": {"N": "0.8609625298888801"}, "steps": {"N": "1188"}, "speed": {"N": "4.943325530462469"}, "calories": {"N": "71.202"}, "ascent": {"N": "6.89699387550354"}, "descent": {"N": "6.908301591873169"}, "pace": {"N": "12.13757816074612"}}}}, {"PutRequest": {"Item": {"user_id": {"S": "72eff89c74cc57178e02f103187ad579"}, "activity_id": {"S": "49257c2476cd5e8d88c7a8c70c4df597"}, "start": {"S": "2017-07-23T21:05:25Z"}, "end": {"S": "2017-07-23T22:06:07.433000Z"}, "type": {"S": "run"}, "distance": {"N": "10.105919747530994"}, "steps": {"N": "9756"}, "speed": {"N": "9.993610992002262"}, "calories": {"N": "873.874"}, "ascent": {"N": "18.73553527146578"}, "descent": {"N": "16.15081837028265"}, "pace": {"N": "6.003835855529809"}}}}, {"PutRequest": {"Item": {"user_id": {"S": "d77908482ed2505ebbf17ef72be2f080"}, "activity_id": {"S": "3b7535a0de8e52c089d1c87fb599b85e"}, "start": {"S": "2018-04-02T19:38:15Z"}, "end": {"S": "2018-04-02T19:48:03.208000Z"}, "type": {"S": "run"}, "distance": {"N": "0.7459285980539972"}, "steps": {"N": "1110"}, "speed": {"N": "4.582496506816366"}, "calories": {"N": "56.821"}, "ascent": {"N": "3.285293233394623"}, "pace": {"N": "13.093299669896375"}, "descent": {"N": "2.144371283054352"}}}}, {"PutRequest": {"Item": {"user_id": {"S": "4e7aaa167b9b5ff7b9b3a22dee8c2085"}, "activity_id": {"S": "fad78bfcfd6d523387d05375e35cc720"}, "start": {"S": "2017-05-24T21:08:47Z"}, "end": {"S": "2017-05-24T21:36:57.488000Z"}, "type": {"S": "run"}, "distance": {"N": "2.540748354724588"}, "steps": {"N": "3040"}, "speed": {"N": "5.716683798130323"}, "calories": {"N": "169.916"}, "ascent": {"N": "15.674052238464355"}, "descent": {"N": "13.169761583209038"}, "pace": {"N": "10.49559536940339"}}}}, {"PutRequest": {"Item": {"user_id": {"S": "72eff89c74cc57178e02f103187ad579"}, "activity_id": {"S": "0a69b9ba317e5dc1976e26ed675e8add"}, "start": {"S": "2016-12-30T16:35:12Z"}, "end": {"S": "2016-12-30T16:50:29.818000Z"}, "type": {"S": "run"}, "distance": {"N": "2.7351609769448895"}, "steps": {"N": "2393"}, "speed": {"N": "10.754448555128434"}, "calories": {"N": "247.192"}, "ascent": {"N": "16.84138458967209"}, "descent": {"N": "18.50317019224167"}, "pace": {"N": "5.57908661633683"}}}}, {"PutRequest": {"Item": {"user_id": {"S": "d77908482ed2505ebbf17ef72be2f080"}, "activity_id": {"S": "1c84a2e331235118926871788822c47d"}, "start": {"S": "2018-01-08T22:57:17Z"}, "end": {"S": "2018-01-08T23:20:59.359000Z"}, "type": {"S": "run"}, "distance": {"N": "1.9188572619389432"}, "steps": {"N": "2628"}, "speed": {"N": "4.906880075650305"}, "calories": {"N": "155.904"}, "ascent": {"N": "15.731247901916504"}, "descent": {"N": "10.009872436523438"}, "pace": {"N": "12.22772904064672"}}}}, {"PutRequest": {"Item": {"user_id": {"S": "c7e962db02da55209f02fe3d8a86c99d"}, "activity_id": {"S": "a767a7ee3b7857beb8f7bbbb177a3a46"}, "start": {"S": "2017-12-19T22:35:20.323000Z"}, "end": {"S": "2017-12-19T23:01:11.031000Z"}, "type": {"S": "run"}, "distance": {"N": "1.8746515628201759"}, "steps": {"N": "2518"}, "speed": {"N": "4.3863212502836255"}, "pace": {"N": "13.678888657806429"}, "calories": {"N": "137.245"}, "ascent": {"N": "16.160430908203125"}, "descent": {"N": "20.657669067382812"}}}}, {"PutRequest": {"Item": {"user_id": {"S": "c7e962db02da55209f02fe3d8a86c99d"}, "activity_id": {"S": "6630c8d631cb5398a3fd6bf02b5a6c0e"}, "start": {"S": "2017-09-19T23:47:22.981000Z"}, "end": {"S": "2017-09-20T00:18:38.052000Z"}, "type": {"S": "training"}, "calories": {"N": "155"}}}}, {"PutRequest": {"Item": {"user_id": {"S": "4e7aaa167b9b5ff7b9b3a22dee8c2085"}, "activity_id": {"S": "8290ade3f9eb5b008921fff2def216b3"}, "start": {"S": "2018-01-04T22:29:09.279000Z"}, "end": {"S": "2018-01-05T00:26:29.069000Z"}, "type": {"S": "run"}, "distance": {"N": "2.4060739559531714"}, "steps": {"N": "3187"}, "speed": {"N": "1.230417003232262"}, "pace": {"N": "48.76395550645197"}, "calories": {"N": "153.206"}, "ascent": {"N": "30.82001495361328"}, "descent": {"N": "30.34703826904297"}}}}, {"PutRequest": {"Item": {"user_id": {"S": "6bd5f3c04e6b5279aca633c2a245dd9c"}, "activity_id": {"S": "837642a5cb055e289e611484b1674362"}, "start": {"S": "2017-07-31T00:49:36.617000Z"}, "end": {"S": "2017-07-31T03:57:41.881000Z"}, "type": {"S": "run"}, "distance": {"N": "24.396969812551564"}, "steps": {"N": "29377"}, "speed": {"N": "7.9742543523087654"}, "pace": {"N": "7.524214471868252"}, "calories": {"N": "1839.672"}, "ascent": {"N": "142.0194091796875"}, "descent": {"N": "144.65013885498047"}}}}, {"PutRequest": {"Item": {"user_id": {"S": "6bd5f3c04e6b5279aca633c2a245dd9c"}, "activity_id": {"S": "b49e872155b054edabc240bbdef805c9"}, "start": {"S": "2017-01-05T16:31:05.127000Z"}, "end": {"S": "2017-01-05T16:44:06.796000Z"}, "type": {"S": "run"}, "distance": {"N": "2.066942634878331"}, "speed": {"N": "9.564258978871454"}, "pace": {"N": "6.273355848325195"}, "calories": {"N": "140.02300000000002"}, "heart_rate": {"N": "168.41666666666666"}}}}, {"PutRequest": {"Item": {"user_id": {"S": "72eff89c74cc57178e02f103187ad579"}, "activity_id": {"S": "8f6d7df035cb504ca56496921a8dbd7d"}, "start": {"S": "2018-04-04T18:36:17Z"}, "end": {"S": "2018-04-04T19:39:56Z"}, "type": {"S": "run"}, "distance": {"N": "9.664509765624999"}, "speed": {"N": "10.25714479842276"}, "calories": {"N": "870.0000000000003"}, "heart_rate": {"N": "161.53446191051995"}, "ascent": {"N": "169.93999671936032"}, "descent": {"N": "170.39999809265137"}, "pace": {"N": "5.8495810656027984"}}}}, {"PutRequest": {"Item": {"user_id": {"S": "4e7aaa167b9b5ff7b9b3a22dee8c2085"}, "activity_id": {"S": "efb3ca17cd6358dda2ca0ed67c9d547b"}, "start": {"S": "2018-03-20T22:01:25.657000Z"}, "end": {"S": "2018-03-20T22:27:17.212000Z"}, "type": {"S": "run"}, "distance": {"N": "2.2176363089671267"}, "steps": {"N": "2824"}, "speed": {"N": "5.16654880628002"}, "pace": {"N": "11.613168141771752"}, "calories": {"N": "137.829"}, "ascent": {"N": "23.545711517333984"}, "descent": {"N": "23.508716583251953"}}}}, {"PutRequest": {"Item": {"user_id": {"S": "72eff89c74cc57178e02f103187ad579"}, "activity_id": {"S": "90689c26467b5dd8959e766cffd98f16"}, "start": {"S": "2017-10-07T16:33:55Z"}, "end": {"S": "2017-10-07T17:51:14Z"}, "type": {"S": "run"}, "distance": {"N": "11.833509765624987"}, "speed": {"N": "9.281184129901952"}, "calories": {"N": "1038.0000000000007"}, "heart_rate": {"N": "160.59076923076924"}, "ascent": {"N": "171.39999923706046"}, "descent": {"N": "160.79999771118156"}, "pace": {"N": "6.4646923453111"}}}}, {"PutRequest": {"Item": {"user_id": {"S": "72eff89c74cc57178e02f103187ad579"}, "activity_id": {"S": "b6c071f49fd452188f0a9c785a7db0ee"}, "start": {"S": "2017-12-02T19:29:43Z"}, "end": {"S": "2017-12-02T21:16:42Z"}, "type": {"S": "run"}, "distance": {"N": "16.580599609375"}, "speed": {"N": "9.48969135035771"}, "calories": {"N": "1394.9999999999998"}, "heart_rate": {"N": "156.8077746077033"}, "ascent": {"N": "605.6800019428132"}, "descent": {"N": "609.6000015422702"}, "pace": {"N": "6.322650314410733"}}}}, {"PutRequest": {"Item": {"user_id": {"S": "72eff89c74cc57178e02f103187ad579"}, "activity_id": {"S": "c96a5b6ffc2f50e79bdf7bcbe1283d89"}, "start": {"S": "2017-11-18T19:10:39Z"}, "end": {"S": "2017-11-18T21:21:10Z"}, "type": {"S": "run"}, "distance": {"N": "21.108779296874978"}, "speed": {"N": "9.72381387955853"}, "calories": {"N": "1700.0000000000023"}, "heart_rate": {"N": "159.84297017650638"}, "ascent": {"N": "380.72000089138766"}, "descent": {"N": "394.5400000855329"}, "pace": {"N": "6.170418391710728"}}}}, {"PutRequest": {"Item": {"user_id": {"S": "4e7aaa167b9b5ff7b9b3a22dee8c2085"}, "activity_id": {"S": "188cb5baaf2e5ba88509224591da9fbc"}, "start": {"S": "2018-01-05T22:32:39.945000Z"}, "end": {"S": "2018-01-05T22:32:39.945000Z"}, "type": {"S": "run"}}}}, {"PutRequest": {"Item": {"user_id": {"S": "6bd5f3c04e6b5279aca633c2a245dd9c"}, "activity_id": {"S": "82b36833a5035a2ba5f16a981f569d16"}, "start": {"S": "2017-07-25T15:04:09.165000Z"}, "end": {"S": "2017-07-25T16:01:33.633000Z"}, "type": {"S": "run"}, "distance": {"N": "7.639454086996565"}, "steps": {"N": "8708"}, "speed": {"N": "8.406999092474317"}, "pace": {"N": "7.136910488513093"}, "calories": {"N": "594.352"}, "ascent": {"N": "45.906890869140625"}, "descent": {"N": "47.7267951965332"}}}}, {"PutRequest": {"Item": {"user_id": {"S": "72eff89c74cc57178e02f103187ad579"}, "activity_id": {"S": "831beb85f48651a0a35baa5d92eade2c"}, "start": {"S": "2017-07-11T01:32:31Z"}, "end": {"S": "2017-07-11T02:31:21.840000Z"}, "type": {"S": "run"}, "distance": {"N": "10.027094221653302"}, "steps": {"N": "9430"}, "speed": {"N": "10.229043963503878"}, "calories": {"N": "874.584"}, "ascent": {"N": "16.39058780670166"}, "descent": {"N": "20.841952204704285"}, "pace": {"N": "5.8656508090172945"}}}}, {"PutRequest": {"Item": {"user_id": {"S": "4e7aaa167b9b5ff7b9b3a22dee8c2085"}, "activity_id": {"S": "c0887f80f64b5922a49e5dd9e5b13dc9"}, "start": {"S": "2016-05-26T20:15:30.326000Z"}, "end": {"S": "2016-05-26T20:30:36.713000Z"}, "type": {"S": "run"}, "ascent": {"N": "15"}, "distance": {"N": "1.2166972729904824"}, "speed": {"N": "4.988775745097896"}, "steps": {"N": "1594"}, "descent": {"N": "25"}, "pace": {"N": "12.026998820092805"}, "calories": {"N": "77.259"}}}}, {"PutRequest": {"Item": {"user_id": {"S": "6bd5f3c04e6b5279aca633c2a245dd9c"}, "activity_id": {"S": "f7bb1241144a5d64a41fe35b955dbaf1"}, "start": {"S": "2017-07-23T14:52:50.933000Z"}, "end": {"S": "2017-07-23T17:02:37.127000Z"}, "type": {"S": "run"}, "distance": {"N": "16.793176089167417"}, "steps": {"N": "19937"}, "speed": {"N": "8.181308280120504"}, "pace": {"N": "7.333790384820488"}, "calories": {"N": "1280.268"}, "ascent": {"N": "30.455490112304688"}, "descent": {"N": "31.140625"}}}}, {"PutRequest": {"Item": {"user_id": {"S": "6bd5f3c04e6b5279aca633c2a245dd9c"}, "activity_id": {"S": "c8040b7f29f654368aa90eb92c6d72be"}, "start": {"S": "2017-07-27T15:05:24.121000Z"}, "end": {"S": "2017-07-27T16:05:00.199000Z"}, "type": {"S": "run"}, "distance": {"N": "5.090839483580318"}, "steps": {"N": "4964"}, "speed": {"N": "10.056409624603493"}, "pace": {"N": "5.966344077035914"}, "calories": {"N": "414.483"}, "ascent": {"N": "61.15299940109253"}, "descent": {"N": "63.79228925704956"}}}}]}